{
    "name": "root",
    "metadata": {
        "timer_format_version": "0.1.0",
        "start_time_seconds": "1673335663",
        "python_version": "3.6.13 |Anaconda, Inc.| (default, Mar 16 2021, 11:37:27) [MSC v.1916 64 bit (AMD64)]",
        "command_line_arguments": "C:\\Users\\rogersb1\\.conda\\envs\\ChoseTheNameThatYouLikeTheMost\\Scripts\\mlagents-learn",
        "mlagents_version": "0.28.0",
        "mlagents_envs_version": "0.28.0",
        "communication_protocol_version": "1.5.0",
        "pytorch_version": "1.10.2+cpu",
        "numpy_version": "1.19.5",
        "end_time_seconds": "1673335726"
    },
    "total": 62.484306499999995,
    "count": 1,
    "self": 0.005359999999996035,
    "children": {
        "run_training.setup": {
            "total": 0.1195895,
            "count": 1,
            "self": 0.1195895
        },
        "TrainerController.start_learning": {
            "total": 62.359357,
            "count": 1,
            "self": 0.00015750000000025466,
            "children": {
                "TrainerController._reset_env": {
                    "total": 62.3591706,
                    "count": 1,
                    "self": 62.3591706
                },
                "TrainerController._save_models": {
                    "total": 2.890000000377313e-05,
                    "count": 1,
                    "self": 2.890000000377313e-05
                }
            }
        }
    }
}